{"name": "هجمات_11_سبتمبر", "id": 1125754, "predecessors": [{"name": "إرهاب_منسوب_للمسلمين_في_الولايات_المتحدة", "id": 2769142}, {"name": "الخلافات_في_إدارة_جورج_بوش_الابن", "id": 7294631}, {"name": "الولايات_المتحدة", "id": 313148}, {"name": "انتحار_في_2001", "id": 6704916}, {"name": "انتحارات_في_ولاية_نيويورك", "id": 1563841}, {"name": "تاريخ_الولايات_المتحدة_(1991–الحاضر)", "id": 2581369}, {"name": "تاريخ_مدينة_نيويورك", "id": 2186136}, {"name": "جرائم_ضد_الإنسانية", "id": 482488}, {"name": "جرائم_كراهية", "id": 2581310}, {"name": "حوادث_طيران_في_الولايات_المتحدة", "id": 435940}, {"name": "حوادث_قتل_مصورة", "id": 1516408}, {"name": "خطف_طائرات", "id": 150137}, {"name": "رئاسة_جورج_بوش_الابن", "id": 2581371}, {"name": "علاقات_دولية_في_2001", "id": 2436799}, {"name": "قتل_جماعي_في_2001", "id": 3238330}, {"name": "قتل_جماعي_في_الولايات_المتحدة", "id": 3081148}, {"name": "قتل_جماعي_في_الولايات_المتحدة_القرن_21", "id": 6636960}, {"name": "قتل_وانتحار_في_الولايات_المتحدة", "id": 3234550}, {"name": "مذابح_في_الولايات_المتحدة", "id": 844925}, {"name": "مركز_التجارة_العالمي", "id": 2935270}, {"name": "معاداة_الأمريكيين", "id": 2158611}, {"name": "معاداة_الغرب", "id": 2205320}, {"name": "منتحرون_في_مدينة_نيويورك", "id": 4048952}, {"name": "هجمات_تنظيم_القاعدة", "id": 3199809}, {"name": "هجمات_على_مبان_ومنشآت_حكومية", "id": 4029653}, {"name": "هجمات_على_مبان_ومنشآت_في_الولايات_المتحدة", "id": 4064858}, {"name": "هجمات_على_منشآت_عسكرية", "id": 3966380}, {"name": "هوليوود", "id": 931027}, {"name": "القتل_حسب_النوع", "id": 3234494}, {"name": "2001_حسب_البلد", "id": 1490543}, {"name": "تاريخ_جنوب_الولايات_المتحدة", "id": 1740380}, {"name": "الولايات_المتحدة_في_2001", "id": 1853853}, {"name": "أصولية_إسلامية", "id": 2495559}, {"name": "جنوب_الولايات_المتحدة", "id": 1563411}, {"name": "إنفاذ_القانون_في_الولايات_المتحدة", "id": 2799255}, {"name": "الموت_في_فرجينيا", "id": 3853267}, {"name": "ألفيات", "id": 584684}, {"name": "إدارة", "id": 30849}, {"name": "الموت_في_ولاية_نيويورك", "id": 4037108}, {"name": "عنف", "id": 329858}, {"name": "الأمريكتان", "id": 1137968}, {"name": "شمال_شرق_الولايات_المتحدة", "id": 1721961}, {"name": "جريمة", "id": 36143}, {"name": "حكومة_الولايات_المتحدة", "id": 1047100}, {"name": "تاريخ", "id": 7594}, {"name": "نزاعات_في_2001", "id": 2306469}, {"name": "الإسلام", "id": 5934}, {"name": "تقانة", "id": 8101}, {"name": "أمريكا_الشمالية", "id": 6853}, {"name": "حوادث_إرهابية", "id": 401594}, {"name": "جرائم_الممتلكات", "id": 1421140}, {"name": "جزر", "id": 6517}, {"name": "سنوات_القرن_21_في_الولايات_المتحدة", "id": 1924526}, {"name": "تاريخ_القانون", "id": 132406}, {"name": "عنف_سياسي_في_الولايات_المتحدة", "id": 3009415}, {"name": "القرن_21", "id": 1470709}, {"name": "تاريخ_أمريكا_الشمالية", "id": 18380}], "successors": [{"name": "مشاركون_في_هجمات_11_سبتمبر", "id": 134464}, {"name": "نظريات_مؤامرة_11_سبتمبر", "id": 1132898}, {"name": "خاطفو_طائرات_هجمات_11_سبتمبر", "id": 1707642}, {"name": "ما_بعد_هجمات_11_سبتمبر", "id": 2581304}, {"name": "مركز_التجارة_العالمي", "id": 2935270}, {"name": "ضحايا_هجمات_11_سبتمبر", "id": 7147615}, {"name": "أشخاص_مرتبطون_بهجمات_11_سبتمبر", "id": 7147620}]}