{"name": "الأمريكتان", "id": 1137968, "predecessors": [{"name": "قارات", "id": 4779}, {"name": "قارات_عظمى", "id": 1144801}, {"name": "الأرض", "id": 495149}], "successors": [{"name": "أمريكا_الشمالية", "id": 6853}, {"name": "أمريكا_الجنوبية", "id": 7174}, {"name": "شعارات_الدول", "id": 190389}, {"name": "دول_سابقة_في_أمريكا_الشمالية", "id": 474646}, {"name": "أمريكا_الوسطى", "id": 583246}, {"name": "أمريكا_اللاتينية", "id": 583250}, {"name": "عملات_الأمريكيتين", "id": 854178}, {"name": "استعمار_الأمريكتين", "id": 1571399}, {"name": "أغان_أمريكية", "id": 1950352}, {"name": "محاصيل_الأمريكتين", "id": 2116477}, {"name": "منظمات_دولية_في_الأمريكتين", "id": 2739707}, {"name": "طيور_الأمريكيتين", "id": 3696997}, {"name": "دول_أمريكا_الشمالية", "id": 6851}, {"name": "دول_الكاريبي", "id": 8549}, {"name": "سانت_كيتس_ونيفيس", "id": 250244}, {"name": "إنكا", "id": 36799}, {"name": "مدن_أمريكية", "id": 8380}, {"name": "جغرافيا_أمريكا_الشمالية", "id": 38615}, {"name": "تاريخ_الأمريكيين_الأصليين", "id": 992380}, {"name": "تاريخ_شعوب_أصلية_في_الأمريكتين", "id": 4101447}, {"name": "تاريخ_أمريكا_الشمالية", "id": 18380}, {"name": "تاريخ_أمريكا_الجنوبية", "id": 18381}, {"name": "تاريخ_فنزويلا", "id": 39133}, {"name": "تاريخ_بوليفيا", "id": 558403}, {"name": "تاريخ_السلفادور", "id": 576239}, {"name": "تاريخ_البرازيل", "id": 596491}, {"name": "تاريخ_أمريكا_الوسطى", "id": 992375}, {"name": "تاريخ_الأرجنتين", "id": 1205301}, {"name": "تاريخ_الكاريبي", "id": 1429795}, {"name": "الاستعمار_الإسباني_في_الأمريكيتين", "id": 1789279}, {"name": "كريستوفر_كولومبوس", "id": 2551121}, {"name": "طيور_مهاجرة_(نصف_الكرة_الغربي)", "id": 1422337}, {"name": "سراخس_الأمريكيتين", "id": 3015232}, {"name": "أسماك_أمريكا_الشمالية", "id": 1036193}, {"name": "أسماك_أمريكا_الجنوبية", "id": 2305678}, {"name": "أسماك_الكاريبي", "id": 4145861}, {"name": "سياسة_أمريكا_الوسطى", "id": 1808663}, {"name": "ثقافة_أمريكا_اللاتينية", "id": 587766}, {"name": "مواقع_التراث_العالمي_في_المكسيك", "id": 652920}, {"name": "مواقع_التراث_العالمي_في_البرازيل", "id": 759616}, {"name": "مواقع_التراث_العالمي_في_كندا", "id": 1099676}, {"name": "مواقع_التراث_العالمي_في_تشيلي", "id": 1276553}, {"name": "مواقع_التراث_العالمي_في_الولايات_المتحدة", "id": 1581091}, {"name": "المناطق_البيئية_في_الولايات_المتحدة", "id": 1407762}, {"name": "حضارات_قبل_كولومبية", "id": 864056}, {"name": "ثقافة_أمريكية_أصلية", "id": 1421585}, {"name": "أماكن_مأهولة_في_جرينلاند", "id": 1578215}, {"name": "عواصم_أمريكا_الشمالية", "id": 35791}, {"name": "مدن_كندا", "id": 35792}, {"name": "مدن_المكسيك", "id": 37746}, {"name": "العبودية_في_الولايات_المتحدة", "id": 1814728}, {"name": "الحضارات_القديمة_في_أمريكا_الشمالية", "id": 1421560}, {"name": "مواقع_أثرية_في_بيرو", "id": 3861660}, {"name": "طواف_أمريكا_للدراجات", "id": 2982334}, {"name": "دورة_الألعاب_الأمريكية", "id": 2990410}, {"name": "بطولة_أمريكا_الوسطى_والكاريبي_لألعاب_القوى", "id": 3063452}, {"name": "مستعمرات_سابقة_في_أمريكا_الشمالية", "id": 1438380}, {"name": "أقاليم_أو_تبعيات_الكاريبي", "id": 2510660}, {"name": "أساطير_الأسكيمو", "id": 6264029}, {"name": "معاهدات_امتدت_إلى_سان_بيير_وميكلون", "id": 4086903}, {"name": "مستعمرات_سابقة_في_أمريكا_الجنوبية", "id": 2581074}, {"name": "مناطق_في_أمريكا_الجنوبية", "id": 2717208}, {"name": "معاهدات_امتدت_إلى_جزر_فوكلاند", "id": 4086661}, {"name": "معاهدات_امتدت_إلى_غويانا_الفرنسية", "id": 4086684}, {"name": "معاهدات_امتدت_إلى_جورجيا_الجنوبية_وجزر_ساندويتش_الجنوبية", "id": 4144603}, {"name": "اتفاقيات_امتدت_إلى_مستعمرة_سورينام", "id": 7148535}, {"name": "اتفاقيات_امتدت_إلى_غيانا_البريطانية", "id": 7430708}, {"name": "معاهدات_امتدت_إلى_أروبا", "id": 2902554}, {"name": "معاهدات_امتدت_إلى_جزر_الأنتيل_الهولندية", "id": 2902617}, {"name": "معاهدات_امتدت_إلى_الكاريبي_الهولندي", "id": 2902638}, {"name": "معاهدات_امتدت_إلى_مونتسرات", "id": 3944171}, {"name": "معاهدات_امتدت_إلى_جزر_كايمان", "id": 3944172}, {"name": "معاهدات_امتدت_إلى_جزر_العذراء_البريطانية", "id": 3944173}, {"name": "معاهدات_امتدت_إلى_جزر_توركس_وكايكوس", "id": 3944175}, {"name": "معاهدات_امتدت_إلى_جزر_العذراء_الأمريكية", "id": 3944209}, {"name": "معاهدات_امتدت_إلى_غوادلوب", "id": 4086884}, {"name": "معاهدات_امتدت_إلى_مارتينيك", "id": 4086897}, {"name": "معاهدات_امتدت_إلى_بورتوريكو", "id": 4103104}, {"name": "معاهدات_امتدت_إلى_أنغويلا", "id": 4144614}, {"name": "اتفاقيات_امتدت_إلى_كوراساو_والتبعيات", "id": 7430659}, {"name": "إعلام_الولايات_المتحدة", "id": 1986601}, {"name": "سينما_أمريكا_الشمالية", "id": 2394382}, {"name": "مايا", "id": 10566}, {"name": "أساطير_أمريكية_شمالية", "id": 4099372}, {"name": "أساطير_أمريكية_جنوبية", "id": 4145800}, {"name": "مدن_كوبا", "id": 39158}, {"name": "عواصم_دول_الكاريبي", "id": 3246630}, {"name": "صحف_أمريكية", "id": 310241}, {"name": "عملية_كوندور", "id": 4016838}, {"name": "حقوق_الإنسان_في_الولايات_المتحدة", "id": 484918}, {"name": "لاعبات_كرة_مضرب_أرجنتينيات", "id": 2298805}, {"name": "لاعبات_كرة_يد_أرجنتينيات", "id": 3404754}, {"name": "لاعبات_هوكي_ميدان_أرجنتينيات", "id": 5664631}, {"name": "لاعبات_كرة_قدم_أرجنتينيات", "id": 5844935}, {"name": "لاعبات_منتخب_الأرجنتين_لكرة_القدم_للسيدات", "id": 5844934}, {"name": "طيور_الكاريبي", "id": 1429838}, {"name": "بحيرات_الأرجنتين", "id": 1547205}, {"name": "حوض_الأمازون", "id": 1433253}, {"name": "بحيرات_كندا", "id": 1085260}, {"name": "حدائق_كندا_الوطنية", "id": 1099670}, {"name": "جامعات_وكليات_في_الولايات_المتحدة", "id": 1563225}, {"name": "متاحف_الولايات_المتحدة_الأمريكية", "id": 1822721}, {"name": "بحيرات_الولايات_المتحدة_الأمريكية", "id": 1822729}, {"name": "حمامات_طبية_في_الولايات_المتحدة", "id": 8383180}, {"name": "منتجعات_في_وادي_لاس_فيغاس", "id": 4205512}, {"name": "لاعبات_هوكي_ميدان_كنديات", "id": 5672788}, {"name": "احتجاجات_في_الولايات_المتحدة", "id": 1150060}, {"name": "الانتخابات_في_الولايات_المتحدة", "id": 2551988}, {"name": "أحداث_سنوية_في_الولايات_المتحدة", "id": 2821002}, {"name": "هجمات_11_سبتمبر", "id": 1125754}, {"name": "وفيات_عرضية_في_كاليفورنيا", "id": 2010118}, {"name": "وفيات_عرضية_في_فلوريدا", "id": 2010122}, {"name": "وفيات_عرضية_في_إيلينوي", "id": 2010126}, {"name": "وفيات_عرضية_في_ماساشوستس", "id": 2010138}, {"name": "وفيات_عرضية_في_ولاية_نيويورك", "id": 2010146}, {"name": "وفيات_عرضية_في_بنسلفانيا", "id": 2010152}, {"name": "وفيات_عرضية_في_تينيسي", "id": 2010157}, {"name": "وفيات_عرضية_في_فرجينيا", "id": 2010162}, {"name": "وفيات_عرضية_في_ويسكونسن", "id": 2010163}, {"name": "وفيات_ناجمة_عن_الحريق_في_الولايات_المتحدة", "id": 7145183}, {"name": "ضحايا_حوادث_طيران_في_الولايات_المتحدة", "id": 7147629}, {"name": "وفيات_الرياضة_في_كاليفورنيا", "id": 3066249}, {"name": "وفيات_الرياضة_في_إنديانا", "id": 3066254}, {"name": "وفيات_الرياضة_في_ولاية_نيويورك", "id": 3066259}, {"name": "وفيات_عرضية_في_أوهايو", "id": 3988676}, {"name": "وفيات_عرضية_في_تكساس", "id": 4078185}, {"name": "وفيات_عرضية_في_ماريلند", "id": 4154327}, {"name": "وفيات_عرضية_في_ميزوري", "id": 4163496}, {"name": "وفيات_حوادث_الطرق_في_كندا", "id": 7150737}, {"name": "وفيات_عرضية_في_أونتاريو", "id": 4151930}, {"name": "وفيات_حوادث_الطرق_في_البرازيل", "id": 2010064}, {"name": "ضحايا_كارثة_رحلة_خطوط_لاميا_الجوية_2933", "id": 3350243}, {"name": "الألعاب_الأولمبية_الصيفية_2016", "id": 958816}, {"name": "جائحة_فيروس_كورونا_في_أمريكا_الجنوبية", "id": 7323661}, {"name": "مراصد_فلكية_في_تشيلي", "id": 824756}, {"name": "أفلام_مراهقة_أمريكية", "id": 2484482}, {"name": "جوائز_اختيار_المراهقين", "id": 2894492}, {"name": "كشافة_إيغل", "id": 7151549}, {"name": "أشخاص_مرتبطون_بالكشافة_الأمريكية", "id": 7580782}, {"name": "لاعبو_منتخب_تشيلي_لكرة_القدم_للشباب", "id": 3923687}, {"name": "مسلسلات_تلفزيونية_أنتجتها_شركة_كوروس_للترفيه", "id": 3315462}, {"name": "شركات_إعلامية_في_الولايات_المتحدة", "id": 2372732}, {"name": "لاعبو_هوكي_ميدان_في_الألعاب_الأولمبية_الصيفية_1984", "id": 4153275}, {"name": "فائزون_بميداليات_في_الألعاب_الأمريكية_الجنوبية_في_هوكي_الميدان", "id": 5672963}, {"name": "مطبخ_أمريكا_اللاتينية", "id": 815182}, {"name": "مطبخ_أمريكا_الجنوبية", "id": 816307}, {"name": "مهرجانات_أطعمة_ومشروبات_في_الولايات_المتحدة", "id": 4245517}, {"name": "فائزون_بميداليات_في_ألعاب_أمريكا_الوسطى_والكاريبي_في_كرة_المضرب", "id": 7759818}, {"name": "أحداث_يناير_2021_في_الولايات_المتحدة", "id": 7923730}, {"name": "وفيات_حوادث_الطرق_في_المكسيك", "id": 3066069}, {"name": "منافسات_رياضية_في_مدينة_مكسيكو", "id": 4084093}, {"name": "منافسات_رياضية_في_مونتريال", "id": 4205110}, {"name": "مرشحون_في_انتخابات_مجلس_الشيوخ_الأمريكي_2016", "id": 8732395}, {"name": "وفيات_حوادث_الطرق_في_الأرجنتين", "id": 3066062}, {"name": "لاعبو_كرة_قاعدة_في_دورة_الألعاب_الأمريكية_1991", "id": 4164806}, {"name": "فائزون_بميداليات_في_دورة_الألعاب_الأمريكية_في_كرة_القاعدة", "id": 6351470}, {"name": "لاعبو_كرة_قاعدة_في_دورة_الألعاب_الأمريكية_2015", "id": 7307819}, {"name": "لاعبو_كرة_قاعدة_في_دورة_الألعاب_الأمريكية_2011", "id": 7416562}, {"name": "لاعبو_كرة_قاعدة_في_دورة_الألعاب_الأمريكية_1999", "id": 7446493}, {"name": "لاعبو_كرة_قاعدة_في_دورة_الألعاب_الأمريكية_2003", "id": 7504678}, {"name": "لاعبو_كرة_قاعدة_في_دورة_الألعاب_الأمريكية_2007", "id": 7504733}, {"name": "فائزون_بميداليات_في_ألعاب_أمريكا_الوسطى_والكاريبي_في_كرة_القاعدة", "id": 7759691}, {"name": "لاعبو_تيبورونس_ديلا_جويرا", "id": 7387896}, {"name": "لاعبو_اتحاد_رغبي_أرجنتينيون", "id": 4121817}, {"name": "لاعبو_اتحاد_رغبي_دوليون_من_الأرجنتين", "id": 4816404}, {"name": "لاعبو_اتحاد_الرغبي_أمريكيون", "id": 3894201}, {"name": "لاعبو_اتحاد_رغبي_كنديون", "id": 5441781}, {"name": "مدربو_اتحاد_رغبي_أرجنتينيون", "id": 5487519}, {"name": "لاعبو_سباعيات_رغبي_دوليون_من_الولايات_المتحدة", "id": 5646024}, {"name": "لاعبات_اتحاد_رغبي_دوليات_من_كندا", "id": 8727489}, {"name": "لاعبو_سباعيات_رغبي_في_دورة_الألعاب_الأمريكية_2015", "id": 7101607}, {"name": "العنف_ضد_الرجل_في_أمريكا_الشمالية", "id": 7146320}, {"name": "مهربو_مخدرات_مكسيكيون", "id": 3032915}, {"name": "زعماء_مافيا_مكسيكيون", "id": 3032989}, {"name": "نزاعات_في_كندا", "id": 3860427}, {"name": "سجناء_ومعتقلون_في_كندا", "id": 3907109}, {"name": "حالات_أشخاص_مفقودين_في_كندا", "id": 4765549}, {"name": "أشخاص_قتلوا_في_كولومبيا", "id": 3969624}, {"name": "وفيات_بإطلاق_النار_في_كولومبيا", "id": 3971547}, {"name": "جرائم_قتل_غير_محلولة_في_الولايات_المتحدة", "id": 3390987}, {"name": "مهربو_مخدرات_كولومبيون", "id": 4097982}, {"name": "رياضيون_أمريكيون_تناولوا_منشطات", "id": 3113633}, {"name": "وفيات_مرتبطة_بالمخدرات_في_ولاية_نيويورك", "id": 4543273}, {"name": "وفيات_مرتبطة_بالمخدرات_في_كاليفورنيا", "id": 4543314}, {"name": "لاعبو_كرة_قاعدة_في_الألعاب_الأولمبية_الصيفية_1984", "id": 7130413}, {"name": "معاهدات_امتدت_إلى_جرينلاند", "id": 2902680}, {"name": "معاهدات_امتدت_إلى_برمودا", "id": 4086725}, {"name": "اتفاقيات_امتدت_إلى_هندوراس_البريطانية", "id": 7148531}, {"name": "ملاعب_كرة_قدم_في_الولايات_المتحدة", "id": 899185}, {"name": "ملاعب_جمباز_في_الولايات_المتحدة", "id": 4145293}, {"name": "ملاعب_كرة_قدم_في_المكسيك", "id": 900549}, {"name": "ملاعب_الدوري_الإنجليزي_لكرة_القدم_وطنية_سابقة", "id": 6069864}, {"name": "سنترال_بارك", "id": 2997703}, {"name": "ماديسون_سكوير_جاردن", "id": 4023567}, {"name": "ملاعب_كرة_قدم_في_البرازيل", "id": 902074}, {"name": "ملاعب_رياضية_في_ريو_دي_جانيرو_(مدينة)", "id": 3188744}, {"name": "ملاعب_الألعاب_الأولمبية_الصيفية_2016", "id": 3253303}, {"name": "ملاعب_كرة_قدم_في_الأرجنتين", "id": 757932}, {"name": "ملاعب_كرة_قدم_في_تشيلي", "id": 902021}, {"name": "مؤرخو_أمريكا_اللاتينية", "id": 6687431}, {"name": "وثائق_الولايات_المتحدة_التاريخية", "id": 900573}, {"name": "مكتبة_الكونغرس", "id": 1069128}]}