{"name": "سياسيون_فلسطينيون", "id": 11615, "predecessors": [{"name": "سياسيون_عرب", "id": 683024}, {"name": "إنسان", "id": 44473}], "successors": [{"name": "وزراء_حكومة_السلطة_الوطنية_الفلسطينية", "id": 611953}, {"name": "سياسيون_فلسطينيون_مغتالون", "id": 845642}, {"name": "سياسيات_فلسطينيات", "id": 1120876}, {"name": "ياسر_عرفات", "id": 1437778}, {"name": "أعضاء_المجلس_الثوري_لحركة_فتح", "id": 5338866}, {"name": "أعضاء_المجلس_الوطني_الفلسطيني", "id": 6551530}, {"name": "أعضاء_المجلس_التشريعي_الفلسطيني_2006", "id": 861717}, {"name": "أعضاء_المجلس_التشريعي_الفلسطيني_1996", "id": 861858}, {"name": "سياسيون_فلسطينيون_في_القرن_20", "id": 9066820}, {"name": "سياسيون_فلسطينيون_في_القرن_21", "id": 9066822}]}