{"name": "بطولات_الاتحاد_الأوروبي_لكرة_القدم_للأندية", "id": 1263646, "predecessors": [{"name": "منافسات_يويفا", "id": 2458907}, {"name": "اتحادات_رياضية_دولية", "id": 1536407}, {"name": "كرة_القدم", "id": 3145153}], "successors": [{"name": "كأس_السوبر_الأوروبي", "id": 929663}, {"name": "دوري_أبطال_أوروبا_للسيدات", "id": 1200126}, {"name": "الدوري_الأوروبي", "id": 1263643}, {"name": "كأس_الكؤوس_الأوروبية", "id": 2675857}, {"name": "فرق_الدوري_الأوروبي_للشباب", "id": 6075744}, {"name": "كأس_الإنتركونتيننتال", "id": 2269414}, {"name": "كأس_إنترتوتو", "id": 3033800}, {"name": "مواسم_كأس_أوروبا", "id": 3347321}, {"name": "الأندية_الفائزة_بدوري_أبطال_أوروبا_يويفا", "id": 7106540}]}