{"name": "تاريخ_كرة_القدم", "id": 1536495, "predecessors": [{"name": "ألعاب_رياضية_أولمبية", "id": 2092134}, {"name": "تاريخ_اجتماعي", "id": 131001}], "successors": [{"name": "سجلات_وإحصائيات_كرة_القدم", "id": 1711790}, {"name": "مؤسسو_أندية_كرة_قدم", "id": 1740875}, {"name": "نتائج_منتخبات_كرة_قدم_وطنية", "id": 2865709}, {"name": "أندية_كرة_قدم_غير_هابطة", "id": 2919459}, {"name": "خلافات_كرة_القدم", "id": 3081123}, {"name": "منافسات_كرة_قدم_سابقة", "id": 8921935}, {"name": "ملاعب_كرة_قدم_بائدة_في_إنجلترا", "id": 3363159}, {"name": "كؤوس_سوبر_كرة_قدم_وطنية", "id": 742488}, {"name": "نهائيات_كأس_الجزائر", "id": 1511768}, {"name": "نهائيات_كأس_ملك_إسبانيا", "id": 2723033}, {"name": "نهائيات_كأس_الرابطة_الفرنسية", "id": 3256170}, {"name": "نهائيات_كأس_فرنسا", "id": 3257795}, {"name": "مباريات_كرة_قدم_حسمت_بالضربات_الترجيحية", "id": 3328126}, {"name": "قوائم_مباريات_كرة_القدم", "id": 3350740}, {"name": "نهائيات_كأس_إيطاليا", "id": 3534069}, {"name": "نهائيات_كأس_أوكرانيا", "id": 3635081}, {"name": "دربيات_كرة_قدم_دولية", "id": 3321829}, {"name": "مواسم_دوري_أبطال_آسيا", "id": 3067176}, {"name": "مواسم_دوري_الدرجة_الأولى_السعودي", "id": 3782427}, {"name": "كرة_القدم_الآسيوية_في_2023", "id": 3883732}, {"name": "كرة_القدم_في_2009", "id": 586680}, {"name": "كرة_القدم_في_2010", "id": 742429}, {"name": "كرة_القدم_في_2011", "id": 861982}, {"name": "كرة_القدم_في_2012", "id": 903466}, {"name": "كرة_القدم_في_2014", "id": 910484}, {"name": "كرة_القدم_في_2013", "id": 915166}, {"name": "كرة_القدم_في_2015", "id": 968256}, {"name": "كرة_القدم_في_2008", "id": 1144901}, {"name": "كرة_القدم_في_2007", "id": 1149493}, {"name": "كرة_القدم_في_2004", "id": 1407463}, {"name": "كرة_القدم_في_2016", "id": 1508295}, {"name": "كرة_القدم_في_2001", "id": 1758230}, {"name": "كرة_القدم_في_1981", "id": 2002047}, {"name": "كرة_القدم_في_1982", "id": 2002051}, {"name": "كرة_القدم_في_1989", "id": 2002063}, {"name": "كرة_القدم_في_1992", "id": 2002577}, {"name": "كرة_القدم_في_1993", "id": 2002581}, {"name": "كرة_القدم_في_1995", "id": 2002603}, {"name": "كرة_القدم_في_1996", "id": 2002606}, {"name": "كرة_القدم_في_1998", "id": 2002620}, {"name": "كرة_القدم_في_1999", "id": 2002622}, {"name": "كرة_القدم_في_1986", "id": 2003960}, {"name": "كرة_القدم_في_1987", "id": 2003961}, {"name": "كرة_القدم_في_1988", "id": 2003962}, {"name": "كأس_العالم_1990", "id": 149033}, {"name": "أندية_كرة_قدم_أسست_في_1990", "id": 1205261}, {"name": "كؤوس_كرة_قدم_محلية_1989–90", "id": 6026191}, {"name": "كؤوس_كرة_قدم_محلية_1990–91", "id": 6026275}, {"name": "أندية_كرة_قدم_أسست_في_1977", "id": 1205241}, {"name": "كؤوس_كرة_قدم_محلية_1977–78", "id": 6044987}, {"name": "أندية_كرة_قدم_أسست_في_1978", "id": 1205385}, {"name": "كؤوس_كرة_قدم_محلية_1978–79", "id": 6045057}, {"name": "دوريات_كرة_قدم_أوروبية_في_1978–79", "id": 3578512}, {"name": "أندية_كرة_قدم_أسست_في_1979", "id": 1460799}, {"name": "كؤوس_كرة_قدم_محلية_1979–80", "id": 6026300}, {"name": "أندية_كرة_قدم_أسست_في_1980", "id": 1205269}, {"name": "كؤوس_كرة_قدم_محلية_1980–81", "id": 6045058}, {"name": "دوريات_كرة_قدم_أوروبية_في_1980–81", "id": 3578513}, {"name": "كؤوس_كرة_قدم_محلية_1984–85", "id": 6262408}, {"name": "أندية_كرة_قدم_أسست_في_1991", "id": 1205444}, {"name": "كؤوس_كرة_قدم_محلية_1991–92", "id": 6026259}, {"name": "كأس_العالم_1994", "id": 149034}, {"name": "أندية_كرة_قدم_أسست_في_1994", "id": 1288448}, {"name": "كؤوس_كرة_قدم_محلية_1993–94", "id": 6026209}, {"name": "كؤوس_كرة_قدم_محلية_1994–95", "id": 6026312}, {"name": "أندية_كرة_قدم_أسست_في_1997", "id": 1288449}, {"name": "كؤوس_كرة_قدم_محلية_1996–97", "id": 6026212}, {"name": "كؤوس_كرة_قدم_محلية_1997–98", "id": 6026329}, {"name": "أندية_كرة_قدم_أسست_في_1896", "id": 1205379}, {"name": "أندية_كرة_قدم_أسست_في_1908", "id": 259414}, {"name": "أندية_كرة_قدم_أسست_في_1965", "id": 313083}, {"name": "أندية_كرة_قدم_أسست_في_2020", "id": 7245391}, {"name": "أندية_كرة_قدم_انحلت_في_2020", "id": 7556275}, {"name": "أحداث_كرة_قدم_تأجلت_بسبب_جائحة_فيروس_كورونا", "id": 7713870}, {"name": "مواسم_الدوري_الفلسطيني_الممتاز_لقطاع_غزة", "id": 6683149}, {"name": "مواسم_الدوري_الفلسطيني_الممتاز_للضفة_الغربية", "id": 6685935}, {"name": "دوريات_كرة_قدم_أوروبية_في_1961–62", "id": 3578491}, {"name": "دوريات_كرة_قدم_أوروبية_في_1947–48", "id": 3578265}, {"name": "دوريات_كرة_قدم_أوروبية_في_1948–49", "id": 3578266}, {"name": "دوريات_كرة_قدم_أوروبية_في_1962–63", "id": 3578492}, {"name": "دوريات_كرة_قدم_أوروبية_في_1963–64", "id": 3578493}, {"name": "دوريات_كرة_قدم_أوروبية_في_1964–65", "id": 3578494}, {"name": "دوريات_كرة_قدم_أوروبية_في_1965–66", "id": 3578495}, {"name": "دوريات_كرة_قدم_أوروبية_في_1966–67", "id": 3578496}, {"name": "دوريات_كرة_قدم_أوروبية_في_1967–68", "id": 3578497}, {"name": "دوريات_كرة_قدم_أوروبية_في_1968–69", "id": 3578498}, {"name": "دوريات_كرة_قدم_أوروبية_في_1969–70", "id": 3578499}, {"name": "دوريات_كرة_قدم_أوروبية_في_1970–71", "id": 3578500}, {"name": "دوريات_كرة_قدم_أوروبية_في_1971–72", "id": 3578501}, {"name": "دوريات_كرة_قدم_أوروبية_في_1972–73", "id": 3578502}, {"name": "دوريات_كرة_قدم_أوروبية_في_1973–74", "id": 3578503}, {"name": "دوريات_كرة_قدم_أوروبية_في_1974–75", "id": 3578504}, {"name": "دوريات_كرة_قدم_أوروبية_في_1975–76", "id": 3578508}, {"name": "دوريات_كرة_قدم_أوروبية_في_1976–77", "id": 3578509}, {"name": "دوريات_كرة_قدم_أوروبية_في_1977–78", "id": 3578510}, {"name": "دوريات_كرة_قدم_أوروبية_في_1979–80", "id": 3578511}, {"name": "دوريات_كرة_قدم_أوروبية_في_1983–84", "id": 3578516}, {"name": "دوريات_كرة_قدم_أوروبية_في_1984–85", "id": 3578517}, {"name": "دوريات_كرة_قدم_أوروبية_في_1985–86", "id": 3576674}, {"name": "دوريات_كرة_قدم_أوروبية_في_1990–91", "id": 3578523}, {"name": "دوريات_كرة_قدم_آسيوية_في_1991–92", "id": 3024895}, {"name": "دوريات_كرة_قدم_أوروبية_في_1991–92", "id": 3578522}, {"name": "دوريات_كرة_قدم_آسيوية_في_1994–95", "id": 2946407}, {"name": "دوريات_كرة_قدم_أوروبية_في_1994–95", "id": 3578526}, {"name": "دوريات_كرة_قدم_آسيوية_في_1997–98", "id": 2946478}, {"name": "دوريات_كرة_قدم_أوروبية_في_1997–98", "id": 3578530}, {"name": "دوريات_كرة_قدم_آسيوية_في_2000–01", "id": 3024915}, {"name": "دوريات_كرة_قدم_أوروبية_في_2000–01", "id": 3578533}, {"name": "دوريات_كرة_قدم_آسيوية_في_2002–03", "id": 3024952}, {"name": "دوريات_كرة_قدم_أوروبية_في_2002–03", "id": 3578536}, {"name": "دوريات_كرة_قدم_آسيوية_في_2003–04", "id": 2950461}, {"name": "دوريات_كرة_قدم_أوروبية_في_2003–04", "id": 3578537}, {"name": "مواسم_الدوري_السوري_الممتاز", "id": 3250631}, {"name": "مواسم_دوري_السوبر_الأوزبكي", "id": 6705761}, {"name": "مواسم_نادي_ريال_مدريد", "id": 1514316}, {"name": "مواسم_نادي_برشلونة", "id": 2741638}, {"name": "أعضاء_قاعة_مشاهير_كرة_القدم_الإنجليزية", "id": 7597875}, {"name": "مواسم_الدوري_الطاجيكي", "id": 6685714}, {"name": "مواسم_دوري_قرغيزستان_لكرة_القدم", "id": 6685371}, {"name": "مواسم_الدوري_الياباني_لكرة_القدم", "id": 3752409}, {"name": "مواسم_رابطة_كرة_القدم_اليابانية", "id": 6691983}, {"name": "مواسم_دوري_اليابان_لكرة_القدم", "id": 7389010}, {"name": "مواسم_نادي_الزمالك", "id": 3332259}, {"name": "مواسم_نادي_المقاولون_العرب", "id": 3699243}, {"name": "دوريات_كرة_قدم_إفريقية_في_2018-19", "id": 4343021}, {"name": "دوريات_كرة_قدم_أوروبية_في_2018–19", "id": 4393041}, {"name": "دوريات_كرة_قدم_آسيوية_في_2018-19", "id": 4600704}, {"name": "دوريات_كرة_قدم_كاريبية_في_2018–19", "id": 6685901}, {"name": "دوريات_كرة_قدم_محلية_للسيدات_2018–19", "id": 7567837}, {"name": "دوريات_كرة_قدم_أوروبية_في_1926–27", "id": 3578229}, {"name": "دوريات_كرة_قدم_أوروبية_في_1927–28", "id": 3578230}, {"name": "دوريات_كرة_قدم_أوروبية_في_1928–29", "id": 3578231}, {"name": "دوريات_كرة_قدم_أوروبية_في_1929–30", "id": 3578232}, {"name": "دوريات_كرة_قدم_أوروبية_في_1930–31", "id": 3578233}, {"name": "دوريات_كرة_قدم_أوروبية_في_1931–32", "id": 3578234}, {"name": "دوريات_كرة_قدم_أوروبية_في_1932–33", "id": 3578235}, {"name": "دوريات_كرة_قدم_أوروبية_في_1933–34", "id": 3578236}, {"name": "دوريات_كرة_قدم_أوروبية_في_1934–35", "id": 3578237}, {"name": "دوريات_كرة_قدم_أوروبية_في_1935–36", "id": 3578244}, {"name": "دوريات_كرة_قدم_أوروبية_في_1936–37", "id": 3578246}, {"name": "دوريات_كرة_قدم_أوروبية_في_1937–38", "id": 3578247}, {"name": "دوريات_كرة_قدم_أوروبية_في_1938–39", "id": 3578245}, {"name": "دوريات_كرة_قدم_أوروبية_في_1939–40", "id": 3578253}, {"name": "دوريات_كرة_قدم_أوروبية_في_1940–41", "id": 3578257}, {"name": "دوريات_كرة_قدم_أوروبية_في_1941–42", "id": 3578258}, {"name": "دوريات_كرة_قدم_أوروبية_في_1942–43", "id": 3578259}, {"name": "دوريات_كرة_قدم_أوروبية_في_1945–46", "id": 3578263}, {"name": "دوريات_كرة_قدم_أوروبية_في_1946–47", "id": 3578264}, {"name": "دوريات_كرة_قدم_أوروبية_في_1949–50", "id": 3578267}, {"name": "دوريات_كرة_قدم_أوروبية_في_1950–51", "id": 3578268}, {"name": "دوريات_كرة_قدم_أوروبية_في_1951–52", "id": 3578269}, {"name": "دوريات_كرة_قدم_أوروبية_في_1952–53", "id": 3578270}, {"name": "دوريات_كرة_قدم_أوروبية_في_1953–54", "id": 3578272}, {"name": "دوريات_كرة_قدم_أوروبية_في_1954–55", "id": 3578273}, {"name": "دوريات_كرة_قدم_أوروبية_في_1955–56", "id": 3578485}, {"name": "دوريات_كرة_قدم_أوروبية_في_1956–57", "id": 3578486}, {"name": "دوريات_كرة_قدم_أوروبية_في_1957–58", "id": 3578488}, {"name": "دوريات_كرة_قدم_أوروبية_في_1958–59", "id": 3578487}, {"name": "دوريات_كرة_قدم_أوروبية_في_1959–60", "id": 3578489}, {"name": "دوريات_كرة_قدم_أوروبية_في_1960–61", "id": 3578490}, {"name": "لاعبو_كأس_القارات_1997", "id": 1705874}, {"name": "استادات_الدوري_الأمريكي_الشمالي_لكرة_القدم_(1968–84)", "id": 7153177}, {"name": "استادات_الدوري_الأمريكي_الشمالي_لكرة_القدم_(1968–1984)", "id": 7163778}, {"name": "مواسم_كرة_القدم_الأمريكية", "id": 4076657}, {"name": "مواسم_الدوري_الكولومبي_لكرة_القدم", "id": 7389598}, {"name": "كرة_القدم_الأوروغويانية_في_2004", "id": 3881733}, {"name": "مواسم_الدوري_الأوروغواياني_لكرة_القدم", "id": 7353177}, {"name": "كرة_القدم_الرومانية_في_1929–30", "id": 3893136}, {"name": "لاعبو_كأس_أمم_أوروبا_1960", "id": 126121}, {"name": "لاعبو_كأس_أمم_أوروبا_1964", "id": 126126}, {"name": "كرة_القدم_الأوروبية_في_2003–04", "id": 3136836}, {"name": "كؤوس_كرة_قدم_محلية_أوروبية_في_2018–19", "id": 6055947}, {"name": "مباريات_كرة_قدم_في_إيطاليا", "id": 9691349}, {"name": "مباريات_كرة_قدم_في_ويلز", "id": 9691626}, {"name": "كأس_السوبر_الألماني", "id": 2490468}, {"name": "منافسات_كرة_قدم_دولية_للأندية_تستضيفها_ألمانيا", "id": 2727302}, {"name": "نهائيات_كأس_ألمانيا", "id": 5428957}, {"name": "نهائيات_دوري_أبطال_أوروبا", "id": 478257}, {"name": "نهائيات_الدوري_الأوروبي", "id": 1690093}, {"name": "نهائيات_كأس_الكؤوس_الأوروبية", "id": 2733895}]}