{"name": "مشاعر_معادية_لمواطنين", "id": 1697162, "predecessors": [{"name": "العرقية_في_السياسة", "id": 1697173}, {"name": "تحامل", "id": 2581313}, {"name": "تمييز", "id": 36484}, {"name": "علاقات_دولية", "id": 17445}, {"name": "عنصرية", "id": 36482}, {"name": "قومية", "id": 57350}, {"name": "كراهية_الأجانب", "id": 2205325}, {"name": "نقد", "id": 59194}, {"name": "ثقافة", "id": 11535}, {"name": "تقييم", "id": 44439}], "successors": [{"name": "معاداة_السامية", "id": 31386}, {"name": "معاداة_العرب", "id": 521619}, {"name": "معاداة_الصهيونية", "id": 659406}, {"name": "مشاعر_معادية_للإيرانيين", "id": 1072907}, {"name": "مشاعر_معادية_للصين", "id": 1698435}, {"name": "مشاعر_معادية_لبريطانيا", "id": 2094829}, {"name": "معاداة_الأمريكيين", "id": 2158611}, {"name": "معاداة_الغرب", "id": 2205320}, {"name": "معاداة_الأرمن", "id": 3065133}, {"name": "معاداة_الأتراك", "id": 3235412}, {"name": "مشاعر_معادية_للروس", "id": 4393820}, {"name": "مشاعر_معادية_للأوكرانيين", "id": 4393835}, {"name": "انتقادات_الولايات_المتحدة", "id": 4758059}, {"name": "طالبان", "id": 774062}, {"name": "كو_كلوكس_كلان", "id": 2532391}, {"name": "تنظيم_الدولة_الإسلامية_(داعش)", "id": 2580739}, {"name": "مذابح_اليونانيين_البونتيك", "id": 2955614}]}