{"name": "فصائل_مناهضة_للحكومة_في_الحرب_الأهلية_السورية", "id": 1870659, "predecessors": [{"name": "الحرب_الأهلية_السورية", "id": 2349261}, {"name": "المعارضة_السورية", "id": 2757970}, {"name": "منظمات_عصابية_مسلحة", "id": 1490484}, {"name": "وحدات_وفصائل_عسكرية_في_الحرب_الأهلية_السورية", "id": 1870665}, {"name": "تاريخ_سوريا_العسكري", "id": 1551434}], "successors": [{"name": "تنظيم_القاعدة", "id": 27114}, {"name": "الإخوان_المسلمون", "id": 330812}, {"name": "تنظيم_الدولة_الإسلامية_(داعش)", "id": 2580739}, {"name": "الجيش_السوري_الحر", "id": 3063915}, {"name": "الحزب_الإسلامي_التركستاني", "id": 3535650}, {"name": "هيئة_تحرير_الشام", "id": 4026143}]}