{"name": "حلف_شمال_الأطلسي", "id": 202273, "predecessors": [{"name": "أوروبا_الحديثة", "id": 1684607}, {"name": "تاريخ_الولايات_المتحدة_(1945-1964)", "id": 1648682}, {"name": "تحالفات_عسكرية_تشمل_المملكة_المتحدة", "id": 3944141}, {"name": "تحالفات_عسكرية_تشمل_فرنسا", "id": 4145333}, {"name": "تكتل_منظمات", "id": 1477025}, {"name": "علاقات_الاتحاد_السوفيتي_الخارجية", "id": 1805394}, {"name": "معاداة_الشيوعية", "id": 1439399}, {"name": "معاهدات_الحرب_الباردة", "id": 2523067}, {"name": "منظمات_حكومية_دولية_أسست_عبر_معاهدة", "id": 1921113}, {"name": "منظمات_دولية_عسكرية", "id": 1684594}, {"name": "منظمات_مناهضة_للشيوعية", "id": 1997603}, {"name": "الحرب_الباردة", "id": 37248}, {"name": "اتحادات_فوقومية", "id": 1477016}, {"name": "معاهدات", "id": 15638}, {"name": "أوروبا", "id": 6547}, {"name": "تاريخ", "id": 7594}, {"name": "تحالفات_عسكرية", "id": 356770}, {"name": "معاهدات_بلغاريا", "id": 2509450}, {"name": "معاهدات_لوكسمبورغ", "id": 2509132}, {"name": "تاريخ_إيطاليا_العسكري", "id": 1933135}, {"name": "معاهدات_إستونيا", "id": 2509180}, {"name": "معاهدات_بولندا", "id": 2509819}, {"name": "معاهدات_ليتوانيا", "id": 2523081}, {"name": "تاريخ_كندا_العسكري", "id": 1715905}, {"name": "معاهدات_فنلندا", "id": 2509148}, {"name": "معاهدات_البرتغال", "id": 2394804}, {"name": "معاهدات_هولندا", "id": 2523105}, {"name": "معاهدات_بلجيكا", "id": 2509552}, {"name": "تاريخ_إسبانيا_العسكري", "id": 1655152}, {"name": "معاهدات_رومانيا", "id": 2778279}, {"name": "معاهدات_المجر", "id": 2523033}, {"name": "معاهدات_لاتفيا", "id": 2523089}, {"name": "تاريخ_ألمانيا_العسكري", "id": 1267997}, {"name": "تاريخ_اليونان_الحديث", "id": 2117308}, {"name": "معاهدات_كرواتيا", "id": 1985457}, {"name": "معاهدات_الجبل_الأسود", "id": 2509792}, {"name": "معاهدات_جمهورية_مقدونيا", "id": 2510254}, {"name": "معاهدات_سلوفاكيا", "id": 2523148}, {"name": "معاهدات_سلوفينيا", "id": 2523150}, {"name": "معاهدات_ألبانيا", "id": 2523231}, {"name": "معاهدات_الدنمارك", "id": 2509539}, {"name": "معاهدات_آيسلندا", "id": 2523032}, {"name": "معاهدات_التشيك", "id": 1985461}], "successors": [{"name": "دول_أعضاء_في_حلف_شمال_الأطلسي", "id": 1091216}, {"name": "علاقات_الناتو", "id": 2727440}, {"name": "حليف_رئيسي_خارج_الناتو", "id": 7575376}]}