{"name": "أمريكيون_من_أصل_إسكتلندي", "id": 2350578, "predecessors": [{"name": "أمريكيون_من_أصل_أوروبي", "id": 1558772}, {"name": "أمريكيون_من_أصل_بريطاني", "id": 578827}, {"name": "إسكتلنديون", "id": 264972}, {"name": "علم_الأنساب", "id": 992693}, {"name": "أماكن", "id": 615173}, {"name": "إنسان", "id": 44473}], "successors": [{"name": "مهاجرون_إسكتلنديون_إلى_الولايات_المتحدة", "id": 1177053}, {"name": "أمريكيون_من_أصل_إسكتلندي_أيرلندي", "id": 2788379}, {"name": "إسكتلنديون_مغتربون_في_الولايات_المتحدة", "id": 3757392}, {"name": "كوميديون_أمريكيون_من_أصل_إسكتلندي", "id": 9525191}, {"name": "عائلة_كارداشيان", "id": 1247070}, {"name": "أسرة_روزفلت", "id": 1804836}, {"name": "عائلة_ترامب", "id": 2818425}, {"name": "عائلة_فوربس", "id": 4017522}, {"name": "رونالد_ريغان", "id": 538336}]}