{"name": "كائنات_حية_مائية", "id": 260681, "predecessors": [{"name": "تطور_أحيائي", "id": 1425267}, {"name": "علم_البيئة_المائي", "id": 558445}, {"name": "ماء", "id": 180287}, {"name": "كائنات_حية", "id": 260679}, {"name": "علم_الأحياء_التطوري", "id": 44736}], "successors": [{"name": "أسماك", "id": 26699}, {"name": "رخويات", "id": 190824}, {"name": "نباتات_مائية", "id": 194720}, {"name": "طيور_مائية", "id": 198970}, {"name": "كائنات_بحرية", "id": 232079}, {"name": "طحالب", "id": 425886}, {"name": "علم_العوالق", "id": 1165540}, {"name": "قضاعات", "id": 1332914}, {"name": "كائنات_مائية_خيالية", "id": 1843647}, {"name": "حيوانات_بحرية", "id": 282854}, {"name": "لاسعات", "id": 592605}, {"name": "ضفادع", "id": 257740}, {"name": "قيطم", "id": 1697709}, {"name": "فصائل_البرمائيات", "id": 1698048}, {"name": "أجناس_البرمائيات", "id": 1698049}, {"name": "ضفادع_حقيقية", "id": 1699130}, {"name": "ضفدع_حقيقي", "id": 1699475}, {"name": "ضفدعيات_حقيقية", "id": 1699492}, {"name": "بوابة_زواحف_وبرمائيات", "id": 2771411}, {"name": "برمائيات_الولايات_المتحدة", "id": 2121202}, {"name": "برمائيات_المكسيك", "id": 3103535}, {"name": "برمائيات_أمريكا_الجنوبية", "id": 1033331}, {"name": "برمائيات_آسيا", "id": 2307992}, {"name": "برمائيات_أوروبا", "id": 2308633}, {"name": "ضفادع_في_إفريقيا", "id": 4196435}, {"name": "شعاب_مرجانية", "id": 1675250}, {"name": "مأكولات_بحرية", "id": 710520}, {"name": "بط_خيالي", "id": 2489835}, {"name": "شخصيات_تحت_البحر_خيالية", "id": 3698507}, {"name": "أفلام_عن_قرش", "id": 7256765}, {"name": "حوريات_بحر", "id": 967978}]}