{"name": "وحدوية", "id": 2838777, "predecessors": [{"name": "العرقية_في_السياسة", "id": 1697173}, {"name": "جغرافيا_ثقافية", "id": 1241471}, {"name": "سياسات_الهوية", "id": 1446312}, {"name": "صراع_عرقي", "id": 2635417}, {"name": "عموم_القومية", "id": 2590682}, {"name": "مناطق_نزاع", "id": 33858}, {"name": "مناطق_نفوذ_ثقافي", "id": 1262849}, {"name": "نزاع_تاريخي_(إنكار_المجزرة)", "id": 1993690}, {"name": "نزاعات_دولية", "id": 61552}, {"name": "نظرية_العلاقات_الدولية", "id": 1557781}, {"name": "تاريخ_العالم", "id": 3875642}, {"name": "حرب", "id": 206761}, {"name": "جغرافيا_سياسية", "id": 30594}], "successors": [{"name": "صهيونية", "id": 31592}, {"name": "قومية_فلسطينية", "id": 1564782}, {"name": "سقوط_الأندلس", "id": 1864512}, {"name": "اتحادات_قومية", "id": 1888156}, {"name": "حرب_ناغورنو_قرة_باغ", "id": 2899255}, {"name": "وحدوية_روسية", "id": 5188684}, {"name": "الأوراسية", "id": 7532083}]}