{"name": "شركات_سعودية", "id": 32746, "predecessors": [{"name": "اقتصاد_السعودية", "id": 678974}, {"name": "شركات", "id": 10435}, {"name": "اقتصاد_الوطن_العربي", "id": 890585}, {"name": "المجتمع_السعودي", "id": 171118}, {"name": "دول_آسيا", "id": 6496}, {"name": "أعمال_تجارية", "id": 856227}], "successors": [{"name": "شركات_طيران_سعودية", "id": 99702}, {"name": "شركات_مدرجة_في_سوق_تداول", "id": 1759165}, {"name": "شركات_مساهمة_سعودية", "id": 1979894}, {"name": "شركات_تملكها_حكومة_السعودية", "id": 3289271}, {"name": "شركات_مقرها_في_الدمام", "id": 4047666}, {"name": "شركات_مقرها_في_الرياض", "id": 4155400}, {"name": "شركات_مقرها_في_جدة", "id": 6632762}, {"name": "شركات_مقرها_في_محافظة_الخبر", "id": 6642312}, {"name": "شركات_تأمين_سعودية", "id": 1002928}, {"name": "شركات_أغذية_سعودية", "id": 4518300}]}