{"name": "محامون_في_القرن_20", "id": 3282185, "predecessors": [{"name": "حقوقيون_في_القرن_20", "id": 3949068}, {"name": "القرن_20", "id": 1418755}, {"name": "محامون", "id": 131060}, {"name": "التاريخ_حسب_الموضوع", "id": 20026}], "successors": [{"name": "محامون_أمريكيون_في_القرن_20", "id": 3282183}, {"name": "محامون_هولنديون_في_القرن_20", "id": 3870050}, {"name": "محامون_كولومبيون_في_القرن_20", "id": 3870087}, {"name": "محامون_ألمان_في_القرن_20", "id": 3870250}, {"name": "محامون_فرنسيون_في_القرن_20", "id": 3870300}, {"name": "محامون_كنديون_في_القرن_20", "id": 3870307}, {"name": "محامون_أرجنتينيون_في_القرن_20", "id": 3870410}, {"name": "محامون_برازيليون_في_القرن_20", "id": 3870464}, {"name": "محامون_فنزويليون_في_القرن_20", "id": 3870663}, {"name": "محامون_أوروغويانيون_في_القرن_20", "id": 3872769}, {"name": "محامون_لبنانيون_في_القرن_20", "id": 3872937}, {"name": "محامون_مكسيكيون_في_القرن_20", "id": 3873027}, {"name": "محامون_إيطاليون_في_القرن_20", "id": 3873826}, {"name": "محامون_هنود_في_القرن_20", "id": 3873832}, {"name": "محامون_بريطانيون_في_القرن_20", "id": 3873997}, {"name": "محامون_سويسريون_في_القرن_20", "id": 4201704}, {"name": "محامون_إسبان_في_القرن_20", "id": 4816355}, {"name": "محامون_أستراليون_في_القرن_20", "id": 4818459}, {"name": "محامون_تشيليون_في_القرن_20", "id": 5450575}, {"name": "محامون_نيوزيلنديون_في_القرن_20", "id": 5486286}, {"name": "محامون_جنوب_إفريقيون_في_القرن_20", "id": 5489293}, {"name": "محامون_نرويجيون_في_القرن_20", "id": 5658699}, {"name": "محامون_برتغاليون_في_القرن_20", "id": 5828730}, {"name": "محامون_نازيون", "id": 7168654}, {"name": "محامون_ماليزيون_في_القرن_20", "id": 8821140}, {"name": "محامون_سوريون_في_القرن_20", "id": 8821143}, {"name": "محامون_مصريون_في_القرن_20", "id": 8828282}, {"name": "محامون_مغاربة_في_القرن_20", "id": 8831109}, {"name": "محامون_تونسيون_في_القرن_20", "id": 8832624}, {"name": "محامون_فلسطينيون_في_القرن_20", "id": 8842721}]}