{"name": "أشخاص_مثليون_من_ألمانيا", "id": 3376145, "predecessors": [{"name": "أعلام_ألمان", "id": 8963949}, {"name": "أوروبا", "id": 6547}, {"name": "إنسان", "id": 44473}], "successors": [{"name": "كتاب_مثليون_من_ألمانيا", "id": 3376120}, {"name": "رياضيون_مثليون_من_ألمانيا", "id": 7258069}, {"name": "فنانون_مثليون_من_ألمانيا", "id": 7468475}, {"name": "موسيقيون_مثليون_من_ألمانيا", "id": 7364240}, {"name": "ممثلون_مثليون_من_ألمانيا", "id": 8527744}, {"name": "أعلام_إل_جي_بي_تي_ألمانية_في_القرن_21", "id": 9113360}, {"name": "أعلام_إل_جي_بي_تي_ألمانية_في_القرن_20", "id": 9113361}, {"name": "أعلام_إل_جي_بي_تي_ألمانية_في_القرن_19", "id": 9147769}]}