{"name": "مواليد_في_الهند", "id": 3678532, "predecessors": [{"name": "الهند", "id": 289234}, {"name": "التركيبة_السكانية_حسب_البلد", "id": 1307191}], "successors": [{"name": "مواليد_في_باتنا", "id": 3678859}, {"name": "مواليد_في_فاراناسي", "id": 3679050}, {"name": "مواليد_في_الله_آباد", "id": 3679317}, {"name": "مواليد_في_بنغالور", "id": 3679643}, {"name": "مواليد_في_مومباي", "id": 3679841}, {"name": "مواليد_في_دلهي", "id": 3680223}, {"name": "مواليد_في_أمريتسار", "id": 3680347}, {"name": "مواليد_في_نيودلهي", "id": 3680451}, {"name": "مواليد_في_كلكتا", "id": 3680605}, {"name": "مواليد_في_بريلي_(الهند)", "id": 3686317}, {"name": "مواليد_في_شانديغار", "id": 3693953}, {"name": "مواليد_في_تشيناي", "id": 3694076}, {"name": "مواليد_في_حيدر_آباد", "id": 3694599}, {"name": "مواليد_في_جالاندهار", "id": 3699058}, {"name": "مواليد_في_سري_نكر", "id": 3699682}, {"name": "مواليد_في_لكهنؤ", "id": 3702649}, {"name": "مواليد_في_بونه", "id": 3702654}, {"name": "مواليد_في_أتر_برديش", "id": 3709031}, {"name": "مواليد_في_مانغلور", "id": 3712233}, {"name": "مواليد_في_غوا", "id": 3719662}, {"name": "مواليد_في_ثيروفانانثابورام", "id": 3726217}, {"name": "مواليد_في_بنجاب_(الهند)", "id": 3729518}]}