{"name": "الحياة_النباتية_في_أوروبا", "id": 528992, "predecessors": [{"name": "علم_البيئة", "id": 36470}], "successors": [{"name": "نباتات_تركيا", "id": 1058875}, {"name": "نباتات_فرنسا", "id": 1077749}, {"name": "نباتات_أوكرانيا", "id": 1079264}, {"name": "نباتات_مقدونيا", "id": 1079274}, {"name": "نباتات_صربيا", "id": 1088716}, {"name": "نباتات_النرويج", "id": 1105288}, {"name": "نباتات_السويد", "id": 1105289}, {"name": "نباتات_سويسرا", "id": 1109113}, {"name": "نباتات_النمسا", "id": 1109116}, {"name": "نباتات_فنلندا", "id": 1112429}, {"name": "نباتات_لاتفيا", "id": 1112430}, {"name": "نباتات_آيسلندا", "id": 1112431}, {"name": "نباتات_ليتوانيا", "id": 1112434}, {"name": "نباتات_روسيا_البيضاء", "id": 1158649}, {"name": "نباتات_مولدوفا", "id": 1208208}, {"name": "نباتات_طبية_في_أوروبا", "id": 2119612}, {"name": "نباتات_الحدائق_في_أوروبا", "id": 2119613}, {"name": "نباتات_جبال_الألب", "id": 2184210}, {"name": "أعشاب_أوروبا", "id": 3461894}, {"name": "علم_صناعة_الخمور", "id": 3258406}]}