{"name": "البحر_الأسود", "id": 543228, "predecessors": [{"name": "بحار", "id": 6526}, {"name": "بحار_آسيا", "id": 37991}, {"name": "بحار_أوروبية", "id": 1689250}, {"name": "بحار_المحيط_الأطلسي", "id": 1072135}, {"name": "جغرافيا_أوروبا_الجنوبية", "id": 4393511}, {"name": "جغرافيا_تركيا", "id": 30568}, {"name": "جغرافية_غرب_آسيا", "id": 1525614}, {"name": "دول_أوروبا", "id": 6541}, {"name": "جغرافيا_أوروبا", "id": 38610}, {"name": "آسيا", "id": 6546}, {"name": "إدارة_ويكيبيديا", "id": 267021}], "successors": [{"name": "لغات_أوكرانيا", "id": 24233}, {"name": "تاريخ_أوكرانيا", "id": 236474}, {"name": "سياسة_أوكرانيا", "id": 1054973}, {"name": "ثقافة_أوكرانية", "id": 1221239}, {"name": "مجموعات_عرقية_في_أوكرانيا", "id": 2086556}, {"name": "مواليد_في_أوكرانيا", "id": 3676983}, {"name": "مواليد_في_سامسون", "id": 3688317}, {"name": "أشخاص_من_طرابزون", "id": 3338213}, {"name": "رياضيون_من_محافظة_طرابزون", "id": 9266041}, {"name": "مواليد_في_أماسية", "id": 3688402}, {"name": "مدن_موانئ_في_البحر_الأسود", "id": 7268673}]}