{"name": "أعضاء_برلمان_السويد", "id": 616059, "predecessors": [{"name": "سياسيون_سويديون", "id": 194979}, {"name": "سياسة_أوروبا", "id": 769231}, {"name": "برلمانات_وطنية", "id": 4385359}, {"name": "إنسان", "id": 44473}], "successors": [{"name": "أعضاء_مجلس_أدنى_في_البرلمان_السويدي", "id": 7157367}, {"name": "أعضاء_مجلس_أعلى_في_البرلمان_السويدي", "id": 7157379}, {"name": "عضوات_البرلمان_السويدي", "id": 8964077}, {"name": "أعضاء_البرلمان_السويدي_2002–2006", "id": 9319269}, {"name": "أعضاء_البرلمان_السويدي_2018–2022", "id": 9319321}, {"name": "أعضاء_البرلمان_السويدي_2022–2026", "id": 9319324}, {"name": "أعضاء_البرلمان_السويدي_من_حزب_التجمع_المعتدل", "id": 8964082}]}