{"name": "مقاطعات_أوكرانيا", "id": 619853, "predecessors": [{"name": "تقسيمات_إدارية_من_المستوى_الأول_حسب_البلد", "id": 1163660}, {"name": "تقسيمات_البلدان_في_أوروبا", "id": 1495996}, {"name": "جغرافيا_أوروبا", "id": 38610}], "successors": [{"name": "أشخاص_من_مقاطعة_كييف", "id": 3733619}, {"name": "مدن_مقاطعة_كييف", "id": 2520946}, {"name": "أشخاص_من_مقاطعة_بولتافا", "id": 4221937}, {"name": "مدن_مقاطعة_دنيبروبتروفسك", "id": 3252582}, {"name": "أشخاص_من_خاركيف", "id": 3262239}, {"name": "أشخاص_من_مقاطعة_لفيف", "id": 3712597}, {"name": "رياضيون_من_مقاطعة_سومي", "id": 8761623}, {"name": "محافظة_خاركوف", "id": 2953372}, {"name": "غوبرنيه_شيرنكوف", "id": 4022899}, {"name": "حكومة_بولتافا", "id": 6238577}, {"name": "رياضيون_من_لفيف", "id": 4074778}, {"name": "مدن_مقاطعة_لفيف", "id": 2084883}, {"name": "رياضيون_من_دنيبروبتروفسك", "id": 4205140}, {"name": "لاعبو_نادي_دنيبرو_لكرة_السلة", "id": 7246415}, {"name": "أماكن_مأهولة_في_بروت", "id": 4109788}, {"name": "رياضيون_من_مقاطعة_دنيبروبتروفسك", "id": 8761586}, {"name": "رياضيون_من_دنيبروبتروفسك_أوبلاست", "id": 9188736}, {"name": "محافظة_يكاترينوسلاف", "id": 9592167}, {"name": "رياضيون_من_خاركيف", "id": 4206106}, {"name": "خريجو_جامعة_خاركيف", "id": 4235239}, {"name": "يوروميدان", "id": 1963127}, {"name": "لاعبو_نادي_أوليكساندريا", "id": 7258075}, {"name": "لاعبو_زابوريزيا", "id": 7809058}, {"name": "أشخاص_من_خيرسون", "id": 3681049}, {"name": "رياضيون_من_مقاطعة_خيرسون", "id": 8761599}, {"name": "لاعبو_نادي_فورسكلا_بولتافا", "id": 4288305}, {"name": "أشخاص_من_تشيرنيفتسي", "id": 855519}, {"name": "رياضيون_من_مقاطعة_تشيركاسي", "id": 8761581}, {"name": "أشخاص_من_محافظة_خيرسون", "id": 6238397}, {"name": "لاعبو_هوفيرلا_أزهورود", "id": 7532535}, {"name": "لاعبو_ميوكولايف", "id": 7533593}, {"name": "لاعبو_كرة_قدم_من_تشرنيغوف", "id": 8542083}, {"name": "أشخاص_من_محافظة_كييف", "id": 6238581}, {"name": "لاعبو_كرة_قدم_من_خاركيف", "id": 8777474}, {"name": "رياضيون_من_ميكولايف", "id": 4074844}]}