{"name": "أفلام_إنتاج_2005", "id": 62066, "predecessors": [{"name": "2005", "id": 13368}, {"name": "ثقافة", "id": 11535}, {"name": "إبداع", "id": 30880}], "successors": [{"name": "أفلام_رعب_إنتاج_2005", "id": 1905389}, {"name": "أفلام_مصرية_إنتاج_2005", "id": 1994026}, {"name": "أفلام_مغربية_إنتاج_2005", "id": 3283979}, {"name": "أفلام_درامية_2005", "id": 7391724}, {"name": "أفلام_وثائقية_2005", "id": 7437318}, {"name": "أفلام_مستقلة_2005", "id": 7437320}, {"name": "أعمال_إخراجية_أولى_في_2005", "id": 8090699}, {"name": "أفلام_كوميدية_2005", "id": 9052033}, {"name": "أفلام_أنمي_2005", "id": 3145631}, {"name": "أفلام_إثارة_وحركة_في_2005", "id": 7758841}]}