{"name": "انتحار", "id": 735840, "predecessors": [{"name": "أخلاقيات_الطب", "id": 1045963}, {"name": "أسباب_الموت", "id": 264602}, {"name": "استقلال_ذاتي", "id": 900634}, {"name": "القتل_حسب_النوع", "id": 3234494}, {"name": "صحة_نفسية", "id": 39216}, {"name": "مواضيع_أساسية_في_الأخلاق", "id": 392898}, {"name": "موت", "id": 41323}, {"name": "أعراض_وعلامات_المعرفة_والإدراك_والحالة_العاطفية_والسلوك", "id": 2542553}], "successors": [{"name": "قتل_رحيم", "id": 2717532}, {"name": "انتحارات_مشتركة", "id": 2738208}, {"name": "منتحرات", "id": 713333}, {"name": "منتحرون_ومنتحرات", "id": 5065955}, {"name": "مشاركون_في_هجمات_11_سبتمبر", "id": 134464}, {"name": "هجمات_11_سبتمبر", "id": 1125754}, {"name": "قدماء_منتحرون", "id": 4880349}, {"name": "انتحار_في_عقد_1860", "id": 8030942}, {"name": "انتحار_في_عقد_1890", "id": 8030946}, {"name": "انتحار_في_عقد_1910", "id": 8030954}, {"name": "انتحار_في_عقد_1930", "id": 8030959}, {"name": "انتحار_في_عقد_1880", "id": 8132342}, {"name": "انتحار_في_2019", "id": 6331107}, {"name": "انتحار_في_2018", "id": 6545476}, {"name": "انتحار_في_1997", "id": 6699762}, {"name": "انتحار_في_2009", "id": 6699763}, {"name": "انتحار_في_1995", "id": 6699785}, {"name": "انتحار_في_2001", "id": 6704916}, {"name": "انتحار_في_2007", "id": 7162499}, {"name": "انتحار_في_2011", "id": 7236321}, {"name": "انتحار_في_2004", "id": 7239742}, {"name": "انتحار_في_2003", "id": 7267191}, {"name": "انتحار_في_2020", "id": 7301695}, {"name": "انتحار_في_2006", "id": 7328006}, {"name": "انتحار_في_1996", "id": 7328160}, {"name": "انتحار_في_2012", "id": 7328259}, {"name": "انتحار_في_2015", "id": 7462360}, {"name": "انتحار_في_1987", "id": 7748062}, {"name": "انتحار_في_1989", "id": 7748064}, {"name": "انتحار_في_1993", "id": 7748067}, {"name": "انتحار_في_1980", "id": 7784905}, {"name": "انتحار_في_1982", "id": 7799441}, {"name": "انتحار_في_2013", "id": 7825512}, {"name": "انتحار_في_2010", "id": 7830326}, {"name": "انتحار_في_1977", "id": 7878667}, {"name": "انتحار_في_1945", "id": 7928511}, {"name": "انتحار_في_1970", "id": 8031692}, {"name": "انتحار_في_1932", "id": 8037628}, {"name": "انتحار_في_1938", "id": 8037645}, {"name": "انتحار_في_2022", "id": 8636161}, {"name": "انتحار_في_2021", "id": 9297655}, {"name": "تفجيرات_انتحارية_في_2016", "id": 7302106}, {"name": "منتحرون_بواسطة_يهود_خلال_هولوكوست", "id": 8678626}]}