{"name": "أمريكيون_خياليون", "id": 744787, "predecessors": [{"name": "أمريكيون", "id": 6705}, {"name": "إنسان", "id": 44473}, {"name": "أماكن", "id": 615173}, {"name": "دراسات_حسب_المنطقة", "id": 1443412}], "successors": [{"name": "شخصيات_خيالية_من_كاليفورنيا", "id": 1295623}, {"name": "شخصيات_أمريكية_في_ألعاب_الفيديو", "id": 3065025}, {"name": "مهاجرون_خياليون_إلى_الولايات_المتحدة", "id": 3190805}, {"name": "شخصيات_خيالية_من_ولاية_نيويورك", "id": 4202009}, {"name": "شخصيات_خيالية_من_إلينوي", "id": 4205587}, {"name": "شخصيات_خيالية_من_مدينة_نيويورك", "id": 2494877}, {"name": "شخصيات_خيالية_من_لوس_أنجلوس", "id": 4198865}, {"name": "أمريكيون_أفارقة_خياليون", "id": 1461163}]}