{"name": "أنواع_الفنون_المرئية", "id": 9652458, "predecessors": [{"name": "أنواع_فنية", "id": 1786599}, {"name": "فنون_مرئية", "id": 19177}], "successors": [{"name": "عمارة", "id": 7587}, {"name": "طرز_معمارية", "id": 8455}, {"name": "فن_رقمي", "id": 509560}, {"name": "واقعية_عجائبية", "id": 589250}, {"name": "أنواع_ألعاب_الفيديو", "id": 598902}, {"name": "فن_شعبي", "id": 1054955}, {"name": "ألعاب_الفن", "id": 1102598}, {"name": "فنون_أرضية", "id": 1241490}, {"name": "تصوير_حسب_النوع_الفني", "id": 1672330}, {"name": "فن_سياسي", "id": 1807185}, {"name": "فن_زخرفي", "id": 1855776}, {"name": "فن_الزجاج", "id": 2186774}, {"name": "لوحات_تاريخية", "id": 2504556}, {"name": "فن_تصويري", "id": 2630035}, {"name": "طليعية", "id": 2715067}, {"name": "دادا", "id": 2997275}, {"name": "رمزية", "id": 3080146}, {"name": "فن_عاري", "id": 3116206}, {"name": "فن_عام", "id": 4010839}, {"name": "الفن_العسكري", "id": 7579031}, {"name": "رسامون_ورسامات", "id": 12376}, {"name": "فنانون_تشكيليون", "id": 226262}, {"name": "فنانو_بورتريه", "id": 549684}, {"name": "رسامون_توضيحيون_في_المجال_العلمي", "id": 1488614}, {"name": "فنانون_تصويريون", "id": 2630031}, {"name": "فنانون_تنصيبيون", "id": 3328012}, {"name": "فنانون_أدائيون", "id": 3328016}, {"name": "فنانو_حيوانات", "id": 4099780}, {"name": "فنانون_سياسيون", "id": 4147985}, {"name": "فنانو_الفسيفساء", "id": 7349946}, {"name": "فنانون_من_الغرب_الأمريكي_القديم", "id": 7366265}, {"name": "رموز_دينية", "id": 250012}, {"name": "موسيقى_دينية", "id": 1105002}, {"name": "مانغا", "id": 19030}, {"name": "أنمي", "id": 36822}, {"name": "قصص_مصورة", "id": 61274}, {"name": "كاريكاتير", "id": 231758}, {"name": "رسوم_متحركة", "id": 667788}, {"name": "حائزون_على_جائزة_روبن", "id": 7772885}, {"name": "رسامو_كارتون_كنديون", "id": 2451085}, {"name": "رسامو_كارتون_إنجليز", "id": 2614522}, {"name": "رسامو_كارتون_بريطانيون", "id": 2614529}, {"name": "رسامو_كارتون_فرنسيون", "id": 3165159}, {"name": "رسامو_كارتون_أمريكيون", "id": 3917855}, {"name": "رسامو_كارتون_أستراليون", "id": 5313197}, {"name": "رسامو_كارتون_نيوزيلنديون", "id": 5683302}, {"name": "رسامو_مانغا", "id": 249803}, {"name": "فنانو_قصص_مصورة_أمريكيون", "id": 2899613}, {"name": "صانعو_قصص_مصورة_(العصر_الذهبي)", "id": 2899719}, {"name": "محررو_كتب_قصص_مصورة", "id": 3348899}, {"name": "مبتكرو_قصص_مصورة_مثليون", "id": 7269777}, {"name": "فنانون_يهود", "id": 3024316}, {"name": "فنانون_مسلمون", "id": 3024343}, {"name": "فنانون_بوذيون", "id": 9133931}, {"name": "فنانو_الفيديو", "id": 3259611}, {"name": "جرافيتي", "id": 176063}, {"name": "رسامو_طبيعة_صامتة_أمريكيون", "id": 5646175}, {"name": "لوحات_بحرية", "id": 4486649}, {"name": "سفن_في_الفن", "id": 7147761}, {"name": "رسوم_متحركة_عن_إل_جي_بي_تي", "id": 3924071}, {"name": "المثلية_في_أنمي_ومانغا", "id": 4735254}, {"name": "فنانون_مثليون", "id": 3545580}, {"name": "مصممو_أزياء_مثليون", "id": 7267366}, {"name": "فنانون_مثليون_من_الولايات_المتحدة", "id": 7148922}, {"name": "فنانون_مثليون_من_المملكة_المتحدة", "id": 7154650}, {"name": "فنانون_مثليون_من_كندا", "id": 7312382}, {"name": "فنانون_مثليون_من_ألمانيا", "id": 7468475}, {"name": "فنانون_مثليون_من_فرنسا", "id": 7816548}, {"name": "دراميون_وكتاب_مسرحيون_إل_جي_بي_تي", "id": 7114926}, {"name": "مخرجون_مثليون", "id": 7152088}, {"name": "مخرجو_مسرح_مثليون", "id": 8464707}, {"name": "فنانو_ألعاب_فيديو", "id": 1108499}, {"name": "فنانو_خيال_علمي", "id": 4823398}, {"name": "فنانو_خيال_تأملي_أمريكيون", "id": 4823490}, {"name": "فنانو_خيال_تأملي_بريطانيون", "id": 5850691}]}