{"name": "جيش", "id": 9975, "predecessors": [{"name": "أشكال_القوات_العسكرية", "id": 7360314}, {"name": "عسكرية", "id": 181636}, {"name": "علوم_عسكرية", "id": 10670}, {"name": "إدارة_عامة", "id": 1437212}, {"name": "أسلحة", "id": 12590}], "successors": [{"name": "تاريخ_عسكري", "id": 11519}, {"name": "جيوش", "id": 33579}, {"name": "رتب_عسكرية", "id": 250198}, {"name": "قوات_جوية_حسب_البلد", "id": 323674}, {"name": "قوات_خاصة", "id": 330367}, {"name": "جيوش_حسب_البلد", "id": 1572525}, {"name": "جيوش_منحلة", "id": 1693686}, {"name": "جيوش_تحرير_وطنية", "id": 3164478}, {"name": "أفراد_الجيش_الأمريكي", "id": 2503992}, {"name": "أفراد_الجيش_النرويجي", "id": 3173507}, {"name": "مرتزقة", "id": 32497}, {"name": "فرسان", "id": 999525}, {"name": "جنود_خياليون", "id": 2116237}, {"name": "جنود_أطفال", "id": 3259978}, {"name": "مجندات", "id": 9486572}, {"name": "الجيش_الهندي_أفلام", "id": 4085007}, {"name": "أفلام_عن_القوات_البرية_للولايات_المتحدة", "id": 4945209}, {"name": "أجنحة_عسكرية_لأحزاب_سياسية", "id": 1572428}, {"name": "رؤساء_أركان_الجيش_السوري", "id": 1999499}]}